odoo/addons/project_template/README.rst
odoo/addons/project_template/__init__.py
odoo/addons/project_template/__manifest__.py
odoo/addons/project_template/i18n/de.po
odoo/addons/project_template/i18n/es.po
odoo/addons/project_template/i18n/es_AR.po
odoo/addons/project_template/i18n/fr.po
odoo/addons/project_template/i18n/fr_FR.po
odoo/addons/project_template/i18n/he.po
odoo/addons/project_template/i18n/hr.po
odoo/addons/project_template/i18n/it.po
odoo/addons/project_template/i18n/nl.po
odoo/addons/project_template/i18n/project_template.pot
odoo/addons/project_template/i18n/pt.po
odoo/addons/project_template/i18n/pt_BR.po
odoo/addons/project_template/i18n/sl.po
odoo/addons/project_template/i18n/sv.po
odoo/addons/project_template/models/__init__.py
odoo/addons/project_template/models/project.py
odoo/addons/project_template/models/project_task.py
odoo/addons/project_template/readme/CONTRIBUTORS.md
odoo/addons/project_template/readme/DESCRIPTION.md
odoo/addons/project_template/readme/USAGE.md
odoo/addons/project_template/static/description/icon.png
odoo/addons/project_template/static/description/index.html
odoo/addons/project_template/tests/__init__.py
odoo/addons/project_template/tests/test_project_template.py
odoo/addons/project_template/views/project.xml
odoo_addon_project_template-18.0.1.0.0.2.dist-info/METADATA
odoo_addon_project_template-18.0.1.0.0.2.dist-info/WHEEL
odoo_addon_project_template-18.0.1.0.0.2.dist-info/top_level.txt
odoo_addon_project_template-18.0.1.0.0.2.dist-info/RECORD
